stopit2/__init__.py
stopit2/py.typed
stopit2/signalstop.py
stopit2/threadstop.py
stopit2/utils.py
stopit2-1.1.2.dist-info/METADATA
stopit2-1.1.2.dist-info/WHEEL
stopit2-1.1.2.dist-info/licenses/LICENSE
stopit2-1.1.2.dist-info/RECORD
