Metadata-Version: 2.4
Name: stopit2
Version: 1.1.2
Summary: Timeout control decorator and context managers, raise any exception in another thread
Project-URL: Homepage, https://spraakbanken.gu.se
Project-URL: Repository, https://github.com/spraakbanken/stopit2
Project-URL: Issues, https://github.com/spraakbanken/stopit2/issues
Author-email: Gilles Lenfant <gilles.lenfant@gmail.com>
Maintainer-email: Språkbanken Text <sb-info@svenska.gu.se>, Kristoffer Andersson <kristoffer.andersson@gu.se>
License-Expression: MIT
License-File: LICENSE
Keywords: threads timeout
Classifier: Development Status :: 5 - Production/Stable
Classifier: Intended Audience :: Developers
Classifier: License :: OSI Approved :: MIT License
Classifier: Operating System :: OS Independent
Classifier: Programming Language :: Python
Classifier: Programming Language :: Python :: 3.9
Classifier: Programming Language :: Python :: 3.10
Classifier: Programming Language :: Python :: 3.11
Classifier: Programming Language :: Python :: 3.12
Classifier: Programming Language :: Python :: 3.13
Classifier: Programming Language :: Python :: Implementation :: CPython
Classifier: Topic :: Utilities
Requires-Python: >=3.9
